LICENSE
MANIFEST.in
README.rst
setup.cfg
setup.py
ofxtools/Client.py
ofxtools/Parser.py
ofxtools/Types.py
ofxtools/__init__.py
ofxtools/__version__.py
ofxtools/header.py
ofxtools/lib.py
ofxtools/ofxhome.py
ofxtools/utils.py
ofxtools/config/__init__.py
ofxtools/config/fi.cfg
ofxtools/config/ofxget_example.cfg
ofxtools/models/__init__.py
ofxtools/models/base.py
ofxtools/models/common.py
ofxtools/models/email.py
ofxtools/models/i18n.py
ofxtools/models/ofx.py
ofxtools/models/profile.py
ofxtools/models/signon.py
ofxtools/models/signup.py
ofxtools/models/tax1099.py
ofxtools/models/wrapperbases.py
ofxtools/models/bank/__init__.py
ofxtools/models/bank/interxfer.py
ofxtools/models/bank/mail.py
ofxtools/models/bank/msgsets.py
ofxtools/models/bank/recur.py
ofxtools/models/bank/stmt.py
ofxtools/models/bank/stmtend.py
ofxtools/models/bank/stpchk.py
ofxtools/models/bank/sync.py
ofxtools/models/bank/wire.py
ofxtools/models/bank/xfer.py
ofxtools/models/billpay/__init__.py
ofxtools/models/billpay/common.py
ofxtools/models/billpay/list.py
ofxtools/models/billpay/mail.py
ofxtools/models/billpay/msgsets.py
ofxtools/models/billpay/pmt.py
ofxtools/models/billpay/recur.py
ofxtools/models/billpay/sync.py
ofxtools/models/invest/__init__.py
ofxtools/models/invest/acct.py
ofxtools/models/invest/mail.py
ofxtools/models/invest/msgsets.py
ofxtools/models/invest/openorders.py
ofxtools/models/invest/positions.py
ofxtools/models/invest/securities.py
ofxtools/models/invest/stmt.py
ofxtools/models/invest/transactions.py
ofxtools/scripts/__init__.py
ofxtools/scripts/ofxget.py
ofxtools/scripts/update_fi_cfg.py
ofxtoolslambda.egg-info/PKG-INFO
ofxtoolslambda.egg-info/SOURCES.txt
ofxtoolslambda.egg-info/dependency_links.txt
ofxtoolslambda.egg-info/entry_points.txt
ofxtoolslambda.egg-info/top_level.txt