Metadata-Version: 1.1
Name: ofxtoolslambda
Version: 0.0.2
Summary: Library for working with Open Financial Exchange (OFX) data
Home-page: https://github.com/rmusmanno/ofxtools
Author: Christopher Singley
Author-email: csingley@gmail.com
License: MIT
Download-URL: https://github.com/rmusmanno/ofxtools/tarball/0.0.2
Keywords: ofx,Open Financial Exchange
Platform: UNKNOWN
Classifier: Development Status :: 3 - Alpha
Classifier: Intended Audience :: Developers
Classifier: Intended Audience :: Financial and Insurance Industry
Classifier: Topic :: Software Development :: Libraries :: Python Modules
Classifier: Topic :: Utilities
Classifier: Topic :: Office/Business
Classifier: Topic :: Office/Business :: Financial
Classifier: Topic :: Office/Business :: Financial :: Accounting
Classifier: Topic :: Office/Business :: Financial :: Investment
Classifier: License :: OSI Approved :: MIT License
Classifier: Operating System :: OS Independent
Classifier: Natural Language :: English
Classifier: Programming Language :: Python
Classifier: Programming Language :: Python :: 3 :: Only
Classifier: Programming Language :: Python :: 3.7
